psrpcore/__init__.py
psrpcore/_base.py
psrpcore/_client.py
psrpcore/_clixml_shell.py
psrpcore/_command.py
psrpcore/_crypto.py
psrpcore/_events.py
psrpcore/_exceptions.py
psrpcore/_host.py
psrpcore/_payload.py
psrpcore/_pipeline.py
psrpcore/_server.py
psrpcore/py.typed
psrpcore/types/__init__.py
psrpcore/types/_base.py
psrpcore/types/_collection.py
psrpcore/types/_complex.py
psrpcore/types/_enum.py
psrpcore/types/_host.py
psrpcore/types/_primitive.py
psrpcore/types/_psrp.py
psrpcore/types/_serializer.py
psrpcore-0.3.0.dist-info/LICENSE
psrpcore-0.3.0.dist-info/METADATA
psrpcore-0.3.0.dist-info/WHEEL
psrpcore-0.3.0.dist-info/top_level.txt
psrpcore-0.3.0.dist-info/RECORD
