Metadata-Version: 2.1
Name: psrpcore
Version: 0.3.0
Summary: Core components for the PowerShell Remoting Protocol
Author-email: Jordan Borean <jborean93@gmail.com>
License: MIT License
Project-URL: homepage, https://github.com/jborean93/psrpcore
Project-URL: documentation, https://psrpcore.readthedocs.io/
Keywords: psrp,pwsh,powershell,remoting
Classifier: Development Status :: 4 - Beta
Classifier: License :: OSI Approved :: MIT License
Classifier: Programming Language :: Python :: 3
Classifier: Programming Language :: Python :: 3.8
Classifier: Programming Language :: Python :: 3.9
Classifier: Programming Language :: Python :: 3.10
Classifier: Programming Language :: Python :: 3.11
Classifier: Programming Language :: Python :: 3.12
Requires-Python: >=3.8
License-File: LICENSE
Requires-Dist: cryptography
